nutmeg/__init__.py
nutmeg/processor.py
nutmeg-2018.1.12.dist-info/DESCRIPTION.rst
nutmeg-2018.1.12.dist-info/METADATA
nutmeg-2018.1.12.dist-info/RECORD
nutmeg-2018.1.12.dist-info/WHEEL
nutmeg-2018.1.12.dist-info/metadata.json
nutmeg-2018.1.12.dist-info/top_level.txt
nutmeg-2018.1.12.dist-info/zip-safe
