Metadata-Version: 2.0
Name: nutmeg
Version: 2018.1.12
Summary: Simple video processing tools using Python with fmpeg
Home-page: https://github.com/Who8MyLunch/NutMeg
Author: Pierre V. Villeneuve
Author-email: pierre.villeneuve@gmail.com
License: UNKNOWN
Keywords: video,ffmpeg,intra,clip,probe
Platform: UNKNOWN
Requires-Dist: sarge
Requires-Dist: ordered-namespace
